gtfstools/__init__.py
gtfstools/agency.py
gtfstools/calendar.py
gtfstools/calendar_dates.py
gtfstools/gtfs.py
gtfstools/helpers.py
gtfstools/routes.py
gtfstools/stop_times.py
gtfstools/stops.py
gtfstools/trips.py
gtfstools-0.1.1.dist-info/LICENSE
gtfstools-0.1.1.dist-info/METADATA
gtfstools-0.1.1.dist-info/WHEEL
gtfstools-0.1.1.dist-info/top_level.txt
gtfstools-0.1.1.dist-info/RECORD
