Metadata-Version: 2.1
Name: gtfstools
Version: 0.1.1
Summary: Python GTFS Tools
Author-email: Kevin Nobel <python@2sk.nl>
Project-URL: Homepage, https://github.com/tweska/gtfstools
Project-URL: Bug Tracker, https://github.com/tweska/gtfstools/issues
Classifier: Programming Language :: Python :: 3.8
Classifier: Programming Language :: Python :: 3.9
Classifier: Programming Language :: Python :: 3.10
Classifier: License :: OSI Approved :: MIT License
Classifier: Operating System :: OS Independent
Requires-Python: >=3.8
License-File: LICENSE
